aleksis_meta/__init__.py
aleksis-2025.1.1.dist-info/LICENCE.rst
aleksis-2025.1.1.dist-info/METADATA
aleksis-2025.1.1.dist-info/WHEEL
aleksis-2025.1.1.dist-info/RECORD
