Metadata-Version: 2.3
Name: AlekSIS
Version: 2025.1.1
Summary: Free School Information System Distribution
License: EUPL-1.2-or-later
Keywords: SIS,education,school,digitisation,school apps
Author: Dominik George
Author-email: dominik.george@teckids.org
Maintainer: Jonathan Weth
Maintainer-email: jonathan.weth@teckids.org
Requires-Python: >=3.10,<4.0
Classifier: Development Status :: 5 - Production/Stable
Classifier: Environment :: Web Environment
Classifier: Framework :: Django :: 5.1
Classifier: Intended Audience :: Developers
Classifier: Intended Audience :: Education
Classifier: License :: Other/Proprietary License
Classifier: Programming Language :: Python :: 3
Classifier: Programming Language :: Python :: 3.10
Classifier: Programming Language :: Python :: 3.11
Classifier: Programming Language :: Python :: 3.12
Classifier: Programming Language :: Python :: 3.13
Classifier: Topic :: Education
Requires-Dist: aleksis-app-alsijil (>=4.0.0,<4.1.0)
Requires-Dist: aleksis-app-chronos (>=4.0.1,<4.1.0)
Requires-Dist: aleksis-app-csvimport (>=4.0.0,<4.1.0)
Requires-Dist: aleksis-app-cursus (>=1.0.0,<1.1.0)
Requires-Dist: aleksis-app-dashboardfeeds (>=4.0.0,<4.1.0)
Requires-Dist: aleksis-app-hjelp (>=4.0.0,<4.1.0)
Requires-Dist: aleksis-app-kolego (>=1.0.0,<1.1.0)
Requires-Dist: aleksis-app-ldap (>=4.0.0,<4.1.0)
Requires-Dist: aleksis-app-lesrooster (>=1.0.0,<1.1.0)
Requires-Dist: aleksis-app-matrix (>=3.0.0,<3.1.0)
Requires-Dist: aleksis-app-resint (>=4.0.0,<4.1.0)
Requires-Dist: aleksis-core[ldap,s3,sentry] (>=4.0.4,<4.1.0)
Project-URL: Homepage, https://aleksis.org/
Project-URL: Repository, https://edugit.org/AlekSIS/official/AlekSIS
